README.md
setup.py
cPython/__init__.py
cPython/cPython.py
cPython.egg-info/PKG-INFO
cPython.egg-info/SOURCES.txt
cPython.egg-info/dependency_links.txt
cPython.egg-info/requires.txt
cPython.egg-info/top_level.txt