Metadata-Version: 1.0
Name: cPython
Version: 0.0.4
Summary: more common def
Home-page: https://github.com/JxiaoC/cPython
Author: xiaoC
Author-email: i@xiaoc.cn
License: MIT Licence
Keywords: cPython
Platform: any
